asitop/__init__.py
asitop/asitop.py
asitop/parsers.py
asitop/utils.py
asitop-0.0.24.dist-info/LICENSE
asitop-0.0.24.dist-info/METADATA
asitop-0.0.24.dist-info/WHEEL
asitop-0.0.24.dist-info/entry_points.txt
asitop-0.0.24.dist-info/top_level.txt
asitop-0.0.24.dist-info/RECORD
